[
  [
    {
      "c": "#F7A8A8",
      "a": 5,
      "fa": [
        1,
        0,
        0,
        0,
        0,
        0,
        6
      ]
    },
    "COL0\n\n\n\nROW0\n\n0",
    {
      "c": "#F9D1A7"
    },
    "PINKY\n\n\n\nLEFT\n\n1",
    {
      "c": "#F9F3A7"
    },
    "RING\n\n\n\nLEFT\n\n2",
    {
      "c": "#CFF4C7"
    },
    "MIDDLE\n\n\n\nLEFT\n\n3",
    {
      "c": "#B8E8E0"
    },
    "INDEX\n\n\n\nLEFT\n\n4",
    {
      "c": "#D7C7F7"
    },
    "CENTER\n\n\n\nLEFT\n\n5",
    "CENTER\n\n\n\nRIGHT\n\n6",
    {
      "c": "#B8E8E0",
      "sm": "cherry"
    },
    "INDEX\n\n\n\nRIGHT\n\n7",
    {
      "c": "#CFF4C7"
    },
    "MIDDLE\n\n\n\nRIGHT\n\n8",
    {
      "c": "#F9F3A7"
    },
    "RING\n\n\n\nRIGHT\n\n9",
    {
      "c": "#F9D1A7"
    },
    "PINKY\n\n\n\nRIGHT\n\n10",
    {
      "c": "#F7A8A8"
    },
    "COL11\n\n\n\nTOP\n\n11"
  ],
  [
    {
      "a": 7,
      "fa": [
        6
      ]
    },
    "12\n\n\n\nROW1",
    {
      "c": "#F9D1A7"
    },
    "13",
    {
      "c": "#F9F3A7"
    },
    "14",
    {
      "c": "#CFF4C7"
    },
    "15",
    {
      "c": "#B8E8E0",
      "f": 6,
      "n": true
    },
    "16",
    {
      "c": "#D7C7F7",
      "f": 3,
      "fa": [
        6
      ]
    },
    "17",
    "18",
    {
      "c": "#B8E8E0",
      "n": true
    },
    "19",
    {
      "c": "#CFF4C7"
    },
    "20",
    {
      "c": "#F9F3A7"
    },
    "21",
    {
      "c": "#F9D1A7"
    },
    "22",
    {
      "c": "#F7A8A8"
    },
    "23\n\n\n\nHOME"
  ],
  [
    "24\n\n\n\nROW2",
    {
      "c": "#F9D1A7"
    },
    "25",
    {
      "c": "#F9F3A7"
    },
    "26",
    {
      "c": "#CFF4C7"
    },
    "27",
    {
      "c": "#B8E8E0"
    },
    "28",
    {
      "c": "#D7C7F7"
    },
    "29",
    "30",
    {
      "c": "#B8E8E0"
    },
    "31",
    {
      "c": "#CFF4C7"
    },
    "32",
    {
      "c": "#F9F3A7"
    },
    "33",
    {
      "c": "#F9D1A7"
    },
    "34",
    {
      "c": "#F7A8A8"
    },
    "35\n\n\n\nLOWER"
  ],
  [
    "36\n\n\n\nROW3",
    {
      "c": "#F9D1A7"
    },
    "37",
    {
      "c": "#F9F3A7"
    },
    "38",
    {
      "c": "#CFF4C7"
    },
    "39",
    {
      "c": "#D7C7F7"
    },
    "40\n\n\n\nL TH",
    {
      "w": 2
    },
    "41\n\n\n\nCENTER THUMB",
    "42\n\n\n\nR TH",
    {
      "c": "#CFF4C7"
    },
    "43",
    {
      "c": "#F9F3A7"
    },
    "44",
    {
      "c": "#F9D1A7"
    },
    "45",
    {
      "c": "#F7A8A8"
    },
    "46\n\n\n\nBOT"
  ]
]